delta_of_delta
