Metadata-Version: 2.1
Name: delta-of-delta
Version: 2.0.0
Summary: Delta-of-delta
Home-page: https://github.com/blester125/delta-of-delta
Author: blester125
Author-email: blester125@gmail.com
License: MIT
Download-URL: https://github.com/blester125/delta-of-delta/archive/2.0.0.tar.gz
Platform: UNKNOWN
Classifier: Intended Audience :: Science/Research
Classifier: Topic :: Scientific/Engineering
Classifier: Environment :: Console
Classifier: License :: OSI Approved :: MIT License
Classifier: Intended Audience :: Developers
Classifier: Natural Language :: English
Classifier: Programming Language :: Python :: 3 :: Only
Classifier: Development Status :: 3 - Alpha
Requires-Python: >=3.6
Provides-Extra: test
